bamboo_ta/__init__.py
bamboo_ta/bamboo_ta.py
bamboo_ta/candles.py
bamboo_ta/cycles.py
bamboo_ta/momentum.py
bamboo_ta/performance.py
bamboo_ta/statistics.py
bamboo_ta/test.py
bamboo_ta/trend.py
bamboo_ta/utility.py
bamboo_ta/volatility.py
bamboo_ta/volume.py
bamboo_ta/candles/__init__.py
bamboo_ta/candles/candlestick_patterns.py
bamboo_ta/candles/dynamic_exhaustion_bars.py
bamboo_ta/candles/exhaustion_bars.py
bamboo_ta/candles/hansen_heiken_ashi.py
bamboo_ta/candles/heiken_ashi.py
bamboo_ta/candles/linear_regression_candles.py
bamboo_ta/candles/smoothed_heiken_ashi.py
bamboo_ta/cycles/__init__.py
bamboo_ta/cycles/even_better_sinewave.py
bamboo_ta/momentum/__init__.py
bamboo_ta/momentum/absolute_price_oscillator.py
bamboo_ta/momentum/awesome_oscillator.py
bamboo_ta/momentum/balance_of_power.py
bamboo_ta/momentum/bias.py
bamboo_ta/momentum/brar.py
bamboo_ta/momentum/calculate_intraday_momentum_index.py
bamboo_ta/momentum/center_of_gravity.py
bamboo_ta/momentum/chande_forecast_oscillator.py
bamboo_ta/momentum/chande_momentum_oscillator.py
bamboo_ta/momentum/commodity_channel_index.py
bamboo_ta/momentum/coppock_curve.py
bamboo_ta/momentum/correlation_trend_indicator.py
bamboo_ta/momentum/directional_movement.py
bamboo_ta/momentum/efficiency_ratio.py
bamboo_ta/momentum/ehlers_fisher_stochastic_center_of_gravity.py
bamboo_ta/momentum/ehlers_ray_index.py
bamboo_ta/momentum/elliott_wave_oscillator.py
bamboo_ta/momentum/fisher_transform.py
bamboo_ta/momentum/inertia.py
bamboo_ta/momentum/kaufmans_adaptive_moving_average.py
bamboo_ta/momentum/kdj.py
bamboo_ta/momentum/know_sure_thing.py
bamboo_ta/momentum/ma_streak.py
bamboo_ta/momentum/momentum.py
bamboo_ta/momentum/momentum_divergence.py
bamboo_ta/momentum/moving_average_convergence_divergence.py
bamboo_ta/momentum/moving_average_convergence_divergence_leader.py
bamboo_ta/momentum/moving_average_convergence_divergence_v.py
bamboo_ta/momentum/percentage_price_oscillator.py
bamboo_ta/momentum/percentage_volume_oscillator.py
bamboo_ta-0.9.6.dist-info/LICENSE
bamboo_ta-0.9.6.dist-info/METADATA
bamboo_ta-0.9.6.dist-info/WHEEL
bamboo_ta-0.9.6.dist-info/top_level.txt
bamboo_ta-0.9.6.dist-info/RECORD
