Metadata-Version: 2.1
Name: bamboo-ta
Version: 0.9.6
Summary: TA library for Pandas
Home-page: https://github.com/DutchCryptoDad/bamboo-ta
Author: DutchCryptoDad (DCD)
Author-email: <dutchcryptodad@gmail.com>
Keywords: python,pandas,numpy,trading,indicator,technical analysis
Classifier: Development Status :: 2 - Pre-Alpha
Classifier: Intended Audience :: Developers
Classifier: Programming Language :: Python :: 3
Classifier: Operating System :: Unix
Classifier: Operating System :: MacOS :: MacOS X
Classifier: Operating System :: Microsoft :: Windows
License-File: LICENSE
Requires-Dist: numpy
Requires-Dist: pandas
Provides-Extra: def
Requires-Dist: pytest ; extra == 'def'
Requires-Dist: twine ; extra == 'def'
